ibm_watsonx_ai_cli/__init__.py
ibm_watsonx_ai_cli/cli.py
ibm_watsonx_ai_cli/py.typed
ibm_watsonx_ai_cli/commands/__init__.py
ibm_watsonx_ai_cli/commands/apps.py
ibm_watsonx_ai_cli/commands/services.py
ibm_watsonx_ai_cli/commands/templates.py
ibm_watsonx_ai_cli/utils/__init__.py
ibm_watsonx_ai_cli/utils/build_package.py
ibm_watsonx_ai_cli/utils/chat.py
ibm_watsonx_ai_cli/utils/config.py
ibm_watsonx_ai_cli/utils/deploy.py
ibm_watsonx_ai_cli/utils/evaluate.py
ibm_watsonx_ai_cli/utils/github.py
ibm_watsonx_ai_cli/utils/utils.py
ibm_watsonx_ai_cli-0.3.0.dist-info/licenses/LICENSE
ibm_watsonx_ai_cli-0.3.0.dist-info/METADATA
ibm_watsonx_ai_cli-0.3.0.dist-info/WHEEL
ibm_watsonx_ai_cli-0.3.0.dist-info/entry_points.txt
ibm_watsonx_ai_cli-0.3.0.dist-info/top_level.txt
ibm_watsonx_ai_cli-0.3.0.dist-info/RECORD
