Metadata-Version: 2.4
Name: ibm-watsonx-ai-cli
Version: 0.3.0
Summary: CLI for deploying AI services with Agents to watsonx.ai.
Author: IBM
Maintainer-email: Łukasz Ćmielowski <lukasz.cmielowski@pl.ibm.com>, Daniel Ryszka <daniel.ryszka@pl.ibm.com>, Mateusz Szewczyk <mateusz.szewczyk@ibm.com>, Mateusz Świtala <mateusz.switala@ibm.com>
License: BSD-3-Clause
Requires-Python: <3.14,>=3.10
License-File: LICENSE
Requires-Dist: typer<1.0.0,>=0.13.0
Requires-Dist: tomli<3.0.0,>=2.0
Requires-Dist: tomlkit<1.0.0
Requires-Dist: ibm-watsonx-ai>=1.3.18
Requires-Dist: python-dotenv<2.0.0,>=1.1.0
Requires-Dist: setuptools<80.9.0; python_version < "3.13"
Requires-Dist: ibm-watsonx-gov<1.3.0,>=1.2.0; python_version < "3.13"
Requires-Dist: numpy<1.27.0,>=1.26.4; python_version < "3.13"
Requires-Dist: scikit-learn<1.8,>=1.5.1; python_version < "3.13"
Requires-Dist: unitxt<1.27,>=1.22.0; python_version < "3.13"
Requires-Dist: textstat<0.8.0,>=0.7.7; python_version < "3.13"
Requires-Dist: litellm<2.0.0,>=1.48.0; python_version < "3.13"
Requires-Dist: jsonschema<5.0.0,>=4.19.0; python_version < "3.13"
Requires-Dist: nest-asyncio<2.0.0,>=1.6.0; python_version < "3.13"
Dynamic: license-file
